hrefs/__init__.py
hrefs/_hypothesis_plugin.py
hrefs/_util.py
hrefs/errors.py
hrefs/href.py
hrefs/model.py
hrefs/py.typed
hrefs/starlette.py
hrefs-0.14.dist-info/entry_points.txt
hrefs-0.14.dist-info/LICENSE
hrefs-0.14.dist-info/WHEEL
hrefs-0.14.dist-info/METADATA
hrefs-0.14.dist-info/RECORD
