Metadata-Version: 2.1
Name: hrefs
Version: 0.14
Summary: Hyperlinks for pydantic models
Author-email: Jaakko Moisio <jaakko@moisio.fi>
Requires-Python: >=3.9
Classifier: License :: OSI Approved :: MIT License
Classifier: Environment :: Web Environment
Classifier: Framework :: FastAPI
Classifier: Framework :: Pydantic
Classifier: Framework :: Pydantic :: 1
Classifier: Framework :: Pydantic :: 2
Classifier: Framework :: Hypothesis
Classifier: Framework :: Pytest
Classifier: Framework :: tox
Classifier: Intended Audience :: Developers
Classifier: Intended Audience :: Information Technology
Classifier: Programming Language :: Python :: 3
Classifier: Programming Language :: Python :: 3 :: Only
Classifier: Programming Language :: Python :: 3.9
Classifier: Programming Language :: Python :: 3.10
Classifier: Programming Language :: Python :: 3.11
Classifier: Programming Language :: Python :: 3.12
Classifier: Programming Language :: Python :: 3.13
Classifier: Topic :: Internet
Classifier: Topic :: Internet :: WWW/HTTP
Classifier: Topic :: Software Development
Classifier: Topic :: Software Development :: Libraries
Classifier: Topic :: Software Development :: Libraries :: Python Modules
Requires-Dist: pydantic>=1.8
Requires-Dist: starlette
Requires-Dist: sphinx>=8.1 ; extra == "doc" and ( python_version>="3.11")
Requires-Dist: sphinx-rtd-theme>=3.0 ; extra == "doc" and ( python_version>="3.11")
Requires-Dist: tox>=4.24 ; extra == "test"
Requires-Dist: pytest>=8.3 ; extra == "test"
Requires-Dist: hypothesis>=6.125 ; extra == "test"
Requires-Dist: fastapi>=0.115 ; extra == "test"
Requires-Dist: black>=25.1 ; extra == "test"
Requires-Dist: pylint>=3.3 ; extra == "test"
Requires-Dist: mypy>=1.15 ; extra == "test"
Requires-Dist: httpx>=0.28 ; extra == "test"
Requires-Dist: pytest-skip-slow ; extra == "test"
Requires-Dist: coverage>=7.6 ; extra == "test"
Project-URL: Documentation, https://hrefs.readthedocs.io/
Project-URL: Source, https://github.com/jasujm/hrefs
Provides-Extra: doc
Provides-Extra: test
